receptors/__init__.py
receptors/__itinerary/later.S.HTML
receptors/_clique/__init__.py
receptors/_clique/group/__init__.py
receptors/_licenses/gpl-3.0-standalone.html
receptors/_status/DB/records.json
receptors/_status/monitors/status_1.py
receptors/_status/status.proc.py
receptors/license.S.HTML
receptors/mixer.MD
receptors/mixer.S.HTML
receptors-0.0.1.dist-info/METADATA
receptors-0.0.1.dist-info/WHEEL
receptors-0.0.1.dist-info/entry_points.txt
receptors-0.0.1.dist-info/RECORD
